ProjetoNotebook/Analista.py
ProjetoNotebook/Gerente.py
ProjetoNotebook/ProcessoAutomatizado.py
ProjetoNotebook/__init__.py
ProjetoNotebook/Dados/estudantes-pucsp.tsv
ProjetoNotebook/Dados/Processamentos_Feitos/colunas_p.csv
ProjetoNotebook/Dados/Processamentos_Feitos/notas_df.csv
ProjetoNotebook-0.8.7.dist-info/LICENSE.txt
ProjetoNotebook-0.8.7.dist-info/METADATA
ProjetoNotebook-0.8.7.dist-info/WHEEL
ProjetoNotebook-0.8.7.dist-info/entry_points.txt
ProjetoNotebook-0.8.7.dist-info/top_level.txt
ProjetoNotebook-0.8.7.dist-info/RECORD
