Metadata-Version: 2.1
Name: ProjetoNotebook
Version: 0.8.7
Summary: Automação do processo de classificação de solicitações de compra de Notebooks à faculdade -Trabalho Acadêmico Hipotético
Home-page: https://github.com/lc1a/ProjetoNotebook
Author: Lucas Almeida
Author-email: ra00319146@pucsp.edu.br
License: UNKNOWN
Keywords: python,pucsp,cdia
Platform: UNKNOWN
Classifier: Programming Language :: Python :: 3
License-File: LICENSE.txt
Requires-Dist: numpy
Requires-Dist: pandas
Requires-Dist: plotly
Requires-Dist: matplotlib
Requires-Dist: bs4
Requires-Dist: requests
Requires-Dist: sklearn
Requires-Dist: lxml
Requires-Dist: Selenium (==3.141.0)
